{"speakers": [], "chunks": [{"timestamp": [0.0, 12.58], "text": " Rouge, bleu, vert et jaune"}, {"timestamp": [12.58, 15.2], "text": " Ce sont les couleurs que nous connaissons"}, {"timestamp": [15.2, 17.08], "text": " Rouge comme une pomme, bleu comme le ciel"}, {"timestamp": [17.08, 19.38], "text": " Vert comme l'herbe, jaune comme le soleil"}, {"timestamp": [19.38, 20.72], "text": " Apprenons les couleurs"}, {"timestamp": [20.72, 23.06], "text": " Rouge, bleu, vert et jaune"}, {"timestamp": [23.06, 25.7], "text": " Apprenons les couleurs"}, {"timestamp": [25.7, 28.12], "text": " C'est amusant et facile à faire"}, {"timestamp": [28.12, 35.24], "text": " Orange, violet, rose et marron Ce sont les couleurs que nous connaissons"}, {"timestamp": [35.24, 40.06], "text": " Orange comme une carotte, violet comme une fleur Rose comme un bonbon, marron comme un ours"}, {"timestamp": [40.06, 45.62], "text": " Apprenons les couleurs Roug, bleu, vert et jaune"}, {"timestamp": [45.62, 50.38], "text": " Apprenons les couleurs, c'est amusant et facile à faire"}, {"timestamp": [50.38, 55.04], "text": " Noir, noir, gris et beige, ce sont les couleurs que nous voyons"}, {"timestamp": [55.04, 59.24], "text": " Blanc comme la neige, noir comme la nuit, gris comme un nuage, beige comme du blé"}, {"timestamp": [59.24, 63.06], "text": " Apprenons les couleurs, rouge, bleu, vert et jaune"}, {"timestamp": [63.06, 68.12], "text": " Apprenons les couleurs, c'est amusant et facile à faire"}, {"timestamp": [68.12, 74.1], "text": " Apprenons les couleurs, dans le monde autour de nous"}, {"timestamp": [74.1, 78.26], "text": " Apprenons ensemble, c'est facile et c'est cool"}, {"timestamp": [78.26, 83.06], "text": " Apprenons les couleurs, rouge, bleu, vert et jaune"}, {"timestamp": [83.06, 88.12], "text": " Apprenons les couleurs, c'est amusant et facile à faire"}, {"timestamp": [88.12, 92.46], "text": " Orange, violet, rose et marron"}, {"timestamp": [92.46, 95.22], "text": " Ce sont les couleurs que nous connaissons"}, {"timestamp": [95.22, 97.82], "text": " Orange comme une carotte, violet comme une fleur"}, {"timestamp": [97.82, 100.06], "text": " Rose comme un bonbon, marron comme un ours"}, {"timestamp": [100.06, 105.62], "text": " Apprenons les couleurs, rougeouges, bleus, verts et jaunes"}, {"timestamp": [105.62, 110.96], "text": " Apprenons les couleurs, c'est amusant et facile à faire"}, {"timestamp": [110.96, 118.12], "text": " Apprenons les couleurs, dans le monde autour de nous"}, {"timestamp": [118.12, 123.28], "text": " Apprenons ensemble, c'est facile et c'est cool"}, {"timestamp": [124.22, 125.74], "text": " Apprenons les couleurs"}, {"timestamp": [125.74, 128.0], "text": " Rouges, bleus, verts et jaunes"}, {"timestamp": [128.0, 130.74], "text": " Apprenons les couleurs"}, {"timestamp": [130.74, 133.02], "text": " Rouges, bleus, verts et jaunes"}, {"timestamp": [133.02, 135.76], "text": " Apprenons les couleurs"}, {"timestamp": [135.76, 138.06], "text": " C'est amusant et facile à faire"}], "text": " Rouge, bleu, vert et jaune Ce sont les couleurs que nous connaissons Rouge comme une pomme, bleu comme le ciel Vert comme l'herbe, jaune comme le soleil Apprenons les couleurs Rouge, bleu, vert et jaune Apprenons les couleurs C'est amusant et facile à faire Orange, violet, rose et marron Ce sont les couleurs que nous connaissons Orange comme une carotte, violet comme une fleur Rose comme un bonbon, marron comme un ours Apprenons les couleurs Roug, bleu, vert et jaune Apprenons les couleurs, c'est amusant et facile à faire Noir, noir, gris et beige, ce sont les couleurs que nous voyons Blanc comme la neige, noir comme la nuit, gris comme un nuage, beige comme du blé Apprenons les couleurs, rouge, bleu, vert et jaune Apprenons les couleurs, c'est amusant et facile à faire Apprenons les couleurs, dans le monde autour de nous Apprenons ensemble, c'est facile et c'est cool Apprenons les couleurs, rouge, bleu, vert et jaune Apprenons les couleurs, c'est amusant et facile à faire Orange, violet, rose et marron Ce sont les couleurs que nous connaissons Orange comme une carotte, violet comme une fleur Rose comme un bonbon, marron comme un ours Apprenons les couleurs, rougeouges, bleus, verts et jaunes Apprenons les couleurs, c'est amusant et facile à faire Apprenons les couleurs, dans le monde autour de nous Apprenons ensemble, c'est facile et c'est cool Apprenons les couleurs Rouges, bleus, verts et jaunes Apprenons les couleurs Rouges, bleus, verts et jaunes Apprenons les couleurs C'est amusant et facile à faire"}